ankify_roam/__init__.py
ankify_roam/anki.py
ankify_roam/ankifiers.py
ankify_roam/cli.py
ankify_roam/default_models.py
ankify_roam/util.py
ankify_roam/roam/__init__.py
ankify_roam/roam/containers.py
ankify_roam/roam/content.py
ankify_roam-0.1.0.dist-info/LICENSE
ankify_roam-0.1.0.dist-info/METADATA
ankify_roam-0.1.0.dist-info/WHEEL
ankify_roam-0.1.0.dist-info/entry_points.txt
ankify_roam-0.1.0.dist-info/top_level.txt
ankify_roam-0.1.0.dist-info/RECORD
