Metadata-Version: 2.1
Name: ankify-roam
Version: 0.1.0
Summary: A command-line tool which brings flashcards created in Roam to Anki
Home-page: https://github.com/taylormitchell/ankify_roam
Author: Taylor Mitchell
Author-email: taylor.j.mitchell@gmail.com
License: UNKNOWN
Platform: UNKNOWN
Classifier: Programming Language :: Python :: 3
Classifier: License :: OSI Approved :: MIT License
Classifier: Operating System :: OS Independent
Requires-Python: >=3.6
